{"type":"StatusEffectData","label":"Status Effect","emoji":"☠️","color":"#f43f5e","folder":"resources/status-effects","convention":"nome-status.json","fields":[{"key":"effect_id","label":"Effect ID","type":"string"},{"key":"effect_name","label":"Name","type":"string"},{"key":"effect_type","label":"Type","type":"enum","options":["DAMAGE_OVER_TIME","SPEED_MODIFIER","STUN","FRAGILE"]},{"key":"icon","label":"Icon","type":"image"},{"key":"description","label":"Description","type":"text"},{"key":"duration","label":"Duration (s)","type":"float","default":5.0,"hint":"-1 = infinito","group":"Stats"},{"key":"tick_rate","label":"Tick Rate (s)","type":"float","default":1.0,"group":"Stats"},{"key":"value","label":"Value","type":"float","default":5.0,"hint":"Dano ou modificador","group":"Stats"},{"key":"vfx_scene_path","label":"VFX Scene","type":"file","filter":"*.tscn","group":"Visuals"},{"key":"overlay_color","label":"Overlay Color","type":"color","group":"Visuals"},{"key":"state_scene_path","label":"State Scene","type":"file","filter":"*.tscn","hint":"FSM state","group":"System"}]}
